az_account_switcher/__init__.py
az_account_switcher/az_account_switcher.py
az_account_switcher/azure_cli.py
az_account_switcher-1.5.0.dist-info/LICENSE
az_account_switcher-1.5.0.dist-info/METADATA
az_account_switcher-1.5.0.dist-info/WHEEL
az_account_switcher-1.5.0.dist-info/entry_points.txt
az_account_switcher-1.5.0.dist-info/RECORD
