Metadata-Version: 2.3
Name: az-account-switcher
Version: 1.5.0
Summary: Utility to switch Azure subscriptions
License: MIT
Keywords: azure,cli,subscription,management
Author: Alexander Bij
Author-email: Alexander.Bij@gmail.com
Requires-Python: >=3.10
Classifier: License :: OSI Approved :: MIT License
Classifier: Programming Language :: Python :: 3
Classifier: Programming Language :: Python :: 3.10
Classifier: Programming Language :: Python :: 3.11
Classifier: Programming Language :: Python :: 3.12
Classifier: Programming Language :: Python :: 3.13
Requires-Dist: click (>=8.2,<9.0)
Project-URL: Repository, https://github.com/abij/az-account-switcher
